morphomapping/__init__.py
morphomapping/morphomapping.py
morphomapping-0.0.8.dist-info/METADATA
morphomapping-0.0.8.dist-info/WHEEL
morphomapping-0.0.8.dist-info/licenses/LICENSE
morphomapping-0.0.8.dist-info/RECORD
