Metadata-Version: 2.4
Name: morphomapping
Version: 0.0.8
Summary: Analyze ImageStream Data
Project-URL: Homepage, http://github.com/Wguido/MorphoMapping/
Project-URL: BugTracker, http://github.com/Wguido/MorphoMapping/
Author-email: Amelie Bauerdick <Amelie.Bauerdick@stud.uni-heidelberg.de>
License-File: LICENSE
Keywords: analysis,cytometry,imaging flow cytometry
Classifier: License :: OSI Approved :: MIT License
Classifier: Operating System :: OS Independent
Classifier: Programming Language :: Python :: 3
Requires-Python: >=3.9
Requires-Dist: adjusttext
Requires-Dist: bokeh
Requires-Dist: flowkit
Requires-Dist: hdbscan
Requires-Dist: matplotlib
Requires-Dist: numpy
Requires-Dist: openpyxl
Requires-Dist: pandas
Requires-Dist: scikit-learn
Requires-Dist: umap-learn
Provides-Extra: docs
Requires-Dist: docutils<=0.20; extra == 'docs'
Requires-Dist: ipython; extra == 'docs'
Requires-Dist: myst-parser; extra == 'docs'
Requires-Dist: nbsphinx; extra == 'docs'
Requires-Dist: nbsphinx-link; extra == 'docs'
Requires-Dist: pandoc; extra == 'docs'
Requires-Dist: sphinx-autodoc-typehints; extra == 'docs'
Requires-Dist: sphinx-book-theme>=1.0.0; extra == 'docs'
Requires-Dist: sphinx<=7.4; extra == 'docs'
Requires-Dist: sphinxcontrib-bibtex>=1.0.0; extra == 'docs'
